{"bronze_metadata":{"row_id":"NA1_5321846446#4cac7675","region":"na1","tier":"custom_fetch","ingestion_timestamp":"2025-10-21T06:04:43.204415","source":"riot_match_v5","quality_flag":"PASS","governance_tag":"CONFIDENT"},"raw_data":{"metadata":{"dataVersion":"2","matchId":"NA1_5321846446","participants":["GXnlY40aIKhNAMqzHfLVqcGI6EHMcqbBaCJEKC9H4ctHSrSu-jKeSYjX4MuxeXT1_lSR0m0cw3TNGQ","_RpDoeyDcqkHwoUNt50eJYdp5GeNyv7ZkmWrcdHZthdgFHM0zJuqdvI3wrrd566bAG7cZadk45A1fw","9CTD4yr8UZ5AgCgXsEZhCQViAluBxZ7F69tEBoFq7jA0XITiUSZA1KZRJFr7nlZX3Nmjl1hLsbEdeQ","gQvdGllqhzI-EKGDsKPwZ1agj7t6N7sf4Ot8vwXKPYyxz7PRS9vNZyM2E1RtyZnq7j7u1FRwRZzhiA","7OBszlEcstXuVag_dgSSCJ-PySoaTp3XyvyswcClR0Xpe6wbVprvjlTIokEu8MOU0WXUCWzEUV7OPg","il8KkxRNM60ai0qKMaEBTWD8M0E-NQ23cNsgEVlUxjewEDviO07l3bNpPGuLWtdZLFu9Qaux1Zjnhw","LajF-rdN8yrvUzTWx5qA_Xv3iP1NGylRbt21qUwyVG5zzAQz8v9zJ1GefsASo3lex4xMPxRgMgSwKA","aOlhiK29CgG6yRLB8gQ-nPOB-zRy0GvQQcKQ_hjYzvt_QM1BbUUP2zW8dlhF0573c46EiPjk-tteJw","OkHv4J5JcbqQSx9I5Fda7L9rpz4wQcaDVpgDyjtlhEcpdZIM9ExEyrfTpjS6EdsYcZjKX9i5ctKC9A","VJweImMEIgwDU5oaaiRb0cA9aV_VZ4N4XQMyqKodETtZGeRLDdKpYDwFqjICkZTgYwM2PDYpISsMlQ"]},"info":{"endOfGameResult":"GameComplete","gameCreation":1752014108622,"gameDuration":2473,"gameEndTimestamp":1752016614483,"gameId":5321846446,"gameMode":"CLASSIC","gameName":"teambuilder-match-5321846446","gameStartTimestamp":1752014141720,"gameType":"MATCHED_GAME","gameVersion":"15.13.693.4876","mapId":11,"participants":[{"PlayerScore0":0,"PlayerScore1":0,"PlayerScore10":0,"PlayerScore11":0,"PlayerScore2":0,"PlayerScore3":0,"PlayerScore4":0,"PlayerScore5":0,"PlayerScore6":0,"PlayerScore7":0,"PlayerScore8":0,"PlayerScore9":0,"allInPings":0,"assistMePings":0,"assists":6,"baronKills":0,"basicPings":0,"challenges":{"12AssistStreakCount":0,"HealFromMapSources":171.8814697265625,"InfernalScalePickup":0,"SWARM_DefeatAatrox":0,"SWARM_DefeatBriar":0,"SWARM_DefeatMiniBosses":0,"SWARM_EvolveWeapon":0,"SWARM_Have3Passives":0,"SWARM_KillEnemy":0,"SWARM_PickupGold":0,"SWARM_ReachLevel50":0,"SWARM_Survive15Min":0,"SWARM_WinWith5EvolvedWeapons":0,"abilityUses":375,"acesBefore15Minutes":0,"alliedJungleMonsterKills":0,"baronTakedowns":0,"blastConeOppositeOpponentCount":0,"bountyGold":0,"buffsStolen":0,"completeSupportQuestInTime":0,"controlWardsPlaced":0,"damagePerMinute":1197.1519677267233,"damageTakenOnTeamPercentage":0.35607609191186895,"dancedWithRiftHerald":0,"deathsByEnemyChamps":9,"dodgeSkillShotsSmallWindow":0,"doubleAces":0,"dragonTakedowns":1,"earliestBaron":1771.7437100500001,"earliestDragonTakedown":2336.1324166120003,"earlyLaningPhaseGoldExpAdvantage":0,"effectiveHealAndShielding":0,"elderDragonKillsWithOpposingSoul":0,"elderDragonMultikills":0,"enemyChampionImmobilizations":0,"enemyJungleMonsterKills":0,"epicMonsterKillsNearEnemyJungler":0,"epicMonsterKillsWithin30SecondsOfSpawn":0,"epicMonsterSteals":0,"epicMonsterStolenWithoutSmite":0,"firstTurretKilled":1,"firstTurretKilledTime":890.0594295100001,"fistBumpParticipation":0,"flawlessAces":0,"fullTeamTakedown":2,"gameLength":2473.2871889460002,"getTakedownsInAllLanesEarlyJungleAsLaner":0,"goldPerMinute":433.6149010437118,"hadOpenNexus":0,"immobilizeAndKillWithAlly":0,"initialBuffCount":0,"initialCrabCount":0,"jungleCsBefore10Minutes":0,"junglerTakedownsNearDamagedEpicMonster":0,"kTurretsDestroyedBeforePlatesFall":0,"kda":1.4444444444444444,"killAfterHiddenWithAlly":0,"killParticipation":0.2708333333333333,"killedChampTookFullTeamDamageSurvived":0,"killingSprees":0,"killsNearEnemyTurret":1,"killsOnOtherLanesEarlyJungleAsLaner":0,"killsOnRecentlyHealedByAramPack":0,"killsUnderOwnTurret":2,"killsWithHelpFromEpicMonster":0,"knockEnemyIntoTeamAndKill":0,"landSkillShotsEarlyGame":12,"laneMinionsFirst10Minutes":63,"laningPhaseGoldExpAdvantage":0,"legendaryCount":0,"legendaryItemUsed":[3083,3084,3748,2501,3075],"lostAnInhibitor":0,"maxCsAdvantageOnLaneOpponent":2,"maxKillDeficit":2,"maxLevelLeadLaneOpponent":1,"mejaisFullStackInTime":0,"moreEnemyJungleThanOpponent":0,"multiKillOneSpell":0,"multiTurretRiftHeraldCount":0,"multikills":0,"multikillsAfterAggressiveFlash":0,"outerTurretExecutesBefore10Minutes":0,"outnumberedKills":1,"outnumberedNexusKill":0,"perfectDragonSoulsTaken":0,"perfectGame":0,"pickKillWithAlly":6,"playedChampSelectPosition":1,"poroExplosions":0,"quickCleanse":0,"quickFirstTurret":0,"quickSoloKills":0,"riftHeraldTakedowns":0,"saveAllyFromDeath":0,"scuttleCrabKills":0,"skillshotsDodged":6,"skillshotsHit":69,"snowballsHit":0,"soloBaronKills":0,"soloKills":4,"soloTurretsLategame":4,"stealthWardsPlaced":9,"survivedSingleDigitHpCount":0,"survivedThreeImmobilizesInFight":0,"takedownOnFirstTurret":0,"takedowns":13,"takedownsAfterGainingLevelAdvantage":0,"takedownsBeforeJungleMinionSpawn":0,"takedownsFirstXMinutes":4,"takedownsInAlcove":0,"takedownsInEnemyFountain":0,"teamBaronKills":1,"teamDamagePercentage":0.23041255428711258,"teamElderDragonKills":0,"teamRiftHeraldKills":0,"teleportTakedowns":1,"tookLargeDamageSurvived":1,"turretPlatesTaken":0,"turretTakedowns":6,"turretsTakenWithRiftHerald":0,"twentyMinionsIn3SecondsCount":0,"twoWardsOneSweeperCount":0,"unseenRecalls":0,"visionScoreAdvantageLaneOpponent":-0.14813005924224854,"visionScorePerMinute":0.38638136344800045,"voidMonsterKill":0,"wardTakedowns":0,"wardTakedownsBefore20M":0,"wardsGuarded":0},"champExperience":23354,"champLevel":18,"championId":36,"championName":"DrMundo","championTransform":0,"commandPings":3,"consumablesPurchased":2,"damageDealtToBuildings":19266,"damageDealtToObjectives":20056,"damageDealtToTurrets":19266,"damageSelfMitigated":53151,"dangerPings":0,"deaths":9,"detectorWardsPlaced":0,"doubleKills":0,"dragonKills":0,"eligibleForProgression":true,"enemyMissingPings":0,"enemyVisionPings":0,"firstBloodAssist":false,"firstBloodKill":false,"firstTowerAssist":false,"firstTowerKill":false,"gameEndedInEarlySurrender":false,"gameEndedInSurrender":false,"getBackPings":0,"goldEarned":17874,"goldSpent":16400,"holdPings":0,"individualPosition":"TOP","inhibitorKills":3,"inhibitorTakedowns":3,"inhibitorsLost":0,"item0":3748,"item1":3083,"item2":3009,"item3":3084,"item4":2501,"item5":3075,"item6":3340,"itemsPurchased":26,"killingSprees":1,"kills":7,"lane":"TOP","largestCriticalStrike":18,"largestKillingSpree":2,"largestMultiKill":1,"longestTimeSpentLiving":488,"magicDamageDealt":56494,"magicDamageDealtToChampions":23184,"magicDamageTaken":5400,"missions":{"playerScore0":0,"playerScore1":0,"playerScore2":0,"playerScore3":0,"playerScore4":0,"playerScore5":0,"playerScore6":0,"playerScore7":0,"playerScore8":0,"playerScore9":0,"playerScore10":0,"playerScore11":0},"needVisionPings":0,"neutralMinionsKilled":0,"nexusKills":1,"nexusLost":0,"nexusTakedowns":1,"objectivesStolen":0,"objectivesStolenAssists":0,"onMyWayPings":0,"participantId":1,"pentaKills":0,"perks":{"statPerks":{"defense":5001,"flex":5001,"offense":5005},"styles":[{"description":"primaryStyle","selections":[{"perk":8437,"var1":3135,"var2":2438,"var3":0},{"perk":8446,"var1":8962,"var2":0,"var3":0},{"perk":8444,"var1":3406,"var2":0,"var3":0},{"perk":8451,"var1":421,"var2":0,"var3":0}],"style":8400},{"description":"subStyle","selections":[{"perk":8304,"var1":9,"var2":4,"var3":5},{"perk":8345,"var1":3,"var2":0,"var3":252}],"style":8300}]},"physicalDamageDealt":259280,"physicalDamageDealtToChampions":24813,"physicalDamageTaken":86403,"placement":0,"playerAugment1":0,"playerAugment2":0,"playerAugment3":0,"playerAugment4":0,"playerAugment5":0,"playerAugment6":0,"playerSubteamId":0,"profileIcon":5465,"pushPings":0,"puuid":"GXnlY40aIKhNAMqzHfLVqcGI6EHMcqbBaCJEKC9H4ctHSrSu-jKeSYjX4MuxeXT1_lSR0m0cw3TNGQ","quadraKills":0,"retreatPings":0,"riotIdGameName":"ICEchocoIateCake","riotIdTagline":"NA1","role":"SOLO","sightWardsBoughtInGame":0,"spell1Casts":208,"spell2Casts":39,"spell3Casts":117,"spell4Casts":11,"subteamPlacement":0,"summoner1Casts":5,"summoner1Id":4,"summoner2Casts":5,"summoner2Id":12,"summonerId":"E_TL4UeKPWGbPCqn1z7O191x1rYaEPoK9Gs0ZL89IEkLyb8","summonerLevel":539,"summonerName":"","teamEarlySurrendered":false,"teamId":100,"teamPosition":"TOP","timeCCingOthers":21,"timePlayed":2473,"totalAllyJungleMinionsKilled":0,"totalDamageDealt":318600,"totalDamageDealtToChampions":49348,"totalDamageShieldedOnTeammates":0,"totalDamageTaken":101567,"totalEnemyJungleMinionsKilled":0,"totalHeal":23515,"totalHealsOnTeammates":0,"totalMinionsKilled":283,"totalTimeCCDealt":346,"totalTimeSpentDead":398,"totalUnitsHealed":1,"tripleKills":0,"trueDamageDealt":2825,"trueDamageDealtToChampions":1349,"trueDamageTaken":9763,"turretKills":6,"turretTakedowns":6,"turretsLost":5,"unrealKills":0,"visionClearedPings":0,"visionScore":15,"visionWardsBoughtInGame":0,"wardsKilled":0,"wardsPlaced":9,"win":true},{"PlayerScore0":0,"PlayerScore1":0,"PlayerScore10":0,"PlayerScore11":0,"PlayerScore2":0,"PlayerScore3":0,"PlayerScore4":0,"PlayerScore5":0,"PlayerScore6":0,"PlayerScore7":0,"PlayerScore8":0,"PlayerScore9":0,"allInPings":2,"assistMePings":11,"assists":26,"baronKills":1,"basicPings":0,"challenges":{"12AssistStreakCount":0,"HealFromMapSources":489.9228057861328,"InfernalScalePickup":0,"SWARM_DefeatAatrox":0,"SWARM_DefeatBriar":0,"SWARM_DefeatMiniBosses":0,"SWARM_EvolveWeapon":0,"SWARM_Have3Passives":0,"SWARM_KillEnemy":0,"SWARM_PickupGold":0,"SWARM_ReachLevel50":0,"SWARM_Survive15Min":0,"SWARM_WinWith5EvolvedWeapons":0,"abilityUses":444,"acesBefore15Minutes":0,"alliedJungleMonsterKills":95,"baronTakedowns":1,"blastConeOppositeOpponentCount":0,"bountyGold":0,"buffsStolen":2,"completeSupportQuestInTime":0,"controlWardTimeCoverageInRiverOrEnemyHalf":0.7964071611547922,"controlWardsPlaced":3,"damagePerMinute":922.4215010074233,"damageTakenOnTeamPercentage":0.14326699368365756,"dancedWithRiftHerald":0,"deathsByEnemyChamps":7,"dodgeSkillShotsSmallWindow":0,"doubleAces":0,"dragonTakedowns":4,"earliestBaron":1771.7437100500001,"earliestDragonTakedown":918.484371816,"earlyLaningPhaseGoldExpAdvantage":0,"effectiveHealAndShielding":0,"elderDragonKillsWithOpposingSoul":0,"elderDragonMultikills":0,"enemyChampionImmobilizations":21,"enemyJungleMonsterKills":2,"epicMonsterKillsNearEnemyJungler":0,"epicMonsterKillsWithin30SecondsOfSpawn":2,"epicMonsterSteals":0,"epicMonsterStolenWithoutSmite":0,"firstTurretKilled":1,"firstTurretKilledTime":890.0594295100001,"fistBumpParticipation":0,"flawlessAces":0,"fullTeamTakedown":2,"gameLength":2473.2871889460002,"goldPerMinute":418.31463454246233,"hadOpenNexus":0,"immobilizeAndKillWithAlly":13,"initialBuffCount":2,"initialCrabCount":1,"jungleCsBefore10Minutes":58.500000059604645,"junglerKillsEarlyJungle":0,"junglerTakedownsNearDamagedEpicMonster":0,"kTurretsDestroyedBeforePlatesFall":0,"kda":5.142857142857143,"killAfterHiddenWithAlly":7,"killParticipation":0.75,"killedChampTookFullTeamDamageSurvived":0,"killingSprees":1,"killsNearEnemyTurret":2,"killsOnLanersEarlyJungleAsJungler":1,"killsOnRecentlyHealedByAramPack":0,"killsUnderOwnTurret":0,"killsWithHelpFromEpicMonster":0,"knockEnemyIntoTeamAndKill":0,"landSkillShotsEarlyGame":0,"laneMinionsFirst10Minutes":2,"laningPhaseGoldExpAdvantage":0,"legendaryCount":0,"legendaryItemUsed":[6692,6610,3075,3110,3065],"lostAnInhibitor":0,"maxCsAdvantageOnLaneOpponent":2.75,"maxKillDeficit":2,"maxLevelLeadLaneOpponent":1,"mejaisFullStackInTime":0,"moreEnemyJungleThanOpponent":-49.00000008940697,"multiKillOneSpell":0,"multiTurretRiftHeraldCount":0,"multikills":0,"multikillsAfterAggressiveFlash":0,"outerTurretExecutesBefore10Minutes":0,"outnumberedKills":1,"outnumberedNexusKill":0,"perfectDragonSoulsTaken":0,"perfectGame":0,"pickKillWithAlly":27,"playedChampSelectPosition":1,"poroExplosions":0,"quickCleanse":0,"quickFirstTurret":0,"quickSoloKills":0,"riftHeraldTakedowns":0,"saveAllyFromDeath":0,"scuttleCrabKills":2,"skillshotsDodged":28,"skillshotsHit":0,"snowballsHit":0,"soloBaronKills":0,"soloKills":0,"stealthWardsPlaced":12,"survivedSingleDigitHpCount":0,"survivedThreeImmobilizesInFight":1,"takedownOnFirstTurret":0,"takedowns":36,"takedownsAfterGainingLevelAdvantage":0,"takedownsBeforeJungleMinionSpawn":0,"takedownsFirstXMinutes":11,"takedownsInAlcove":0,"takedownsInEnemyFountain":0,"teamBaronKills":1,"teamDamagePercentage":0.17753593520800964,"teamElderDragonKills":0,"teamRiftHeraldKills":0,"tookLargeDamageSurvived":1,"turretPlatesTaken":0,"turretTakedowns":5,"turretsTakenWithRiftHerald":0,"twentyMinionsIn3SecondsCount":0,"twoWardsOneSweeperCount":0,"unseenRecalls":0,"visionScoreAdvantageLaneOpponent":-0.04719185829162598,"visionScorePerMinute":0.8605679563509141,"voidMonsterKill":4,"wardTakedowns":2,"wardTakedownsBefore20M":1,"wardsGuarded":2},"champExperience":20974,"champLevel":18,"championId":59,"championName":"JarvanIV","championTransform":0,"commandPings":10,"consumablesPurchased":4,"damageDealtToBuildings":2448,"damageDealtToObjectives":40505,"damageDealtToTurrets":2448,"damageSelfMitigated":98590,"dangerPings":0,"deaths":7,"detectorWardsPlaced":3,"doubleKills":0,"dragonKills":3,"eligibleForProgression":true,"enemyMissingPings":33,"enemyVisionPings":1,"firstBloodAssist":false,"firstBloodKill":false,"firstTowerAssist":true,"firstTowerKill":false,"gameEndedInEarlySurrender":false,"gameEndedInSurrender":false,"getBackPings":0,"goldEarned":17243,"goldSpent":16075,"holdPings":0,"individualPosition":"JUNGLE","inhibitorKills":0,"inhibitorTakedowns":3,"inhibitorsLost":0,"item0":3075,"item1":3174,"item2":6692,"item3":3110,"item4":6610,"item5":3065,"item6":3340,"itemsPurchased":32,"killingSprees":4,"kills":10,"lane":"JUNGLE","largestCriticalStrike":293,"largestKillingSpree":3,"largestMultiKill":1,"longestTimeSpentLiving":766,"magicDamageDealt":23342,"magicDamageDealtToChampions":3652,"magicDamageTaken":9995,"missions":{"playerScore0":0,"playerScore1":0,"playerScore2":0,"playerScore3":0,"playerScore4":0,"playerScore5":0,"playerScore6":0,"playerScore7":0,"playerScore8":0,"playerScore9":0,"playerScore10":0,"playerScore11":0},"needVisionPings":1,"neutralMinionsKilled":191,"nexusKills":0,"nexusLost":0,"nexusTakedowns":1,"objectivesStolen":0,"objectivesStolenAssists":0,"onMyWayPings":62,"participantId":2,"pentaKills":0,"perks":{"statPerks":{"defense":5001,"flex":5008,"offense":5005},"styles":[{"description":"primaryStyle","selections":[{"perk":8010,"var1":768,"var2":0,"var3":0},{"perk":9111,"var1":2596,"var2":720,"var3":0},{"perk":9104,"var1":8,"var2":50,"var3":0},{"perk":8014,"var1":931,"var2":0,"var3":0}],"style":8000},{"description":"subStyle","selections":[{"perk":8105,"var1":40,"var2":5,"var3":0},{"perk":8143,"var1":1500,"var2":0,"var3":0}],"style":8100}]},"physicalDamageDealt":201697,"physicalDamageDealtToChampions":31273,"physicalDamageTaken":30254,"placement":0,"playerAugment1":0,"playerAugment2":0,"playerAugment3":0,"playerAugment4":0,"playerAugment5":0,"playerAugment6":0,"playerSubteamId":0,"profileIcon":4288,"pushPings":1,"puuid":"_RpDoeyDcqkHwoUNt50eJYdp5GeNyv7ZkmWrcdHZthdgFHM0zJuqdvI3wrrd566bAG7cZadk45A1fw","quadraKills":0,"retreatPings":17,"riotIdGameName":"eseo","riotIdTagline":"NA1","role":"NONE","sightWardsBoughtInGame":0,"spell1Casts":170,"spell2Casts":106,"spell3Casts":146,"spell4Casts":22,"subteamPlacement":0,"summoner1Casts":19,"summoner1Id":11,"summoner2Casts":5,"summoner2Id":4,"summonerId":"x4Co4RrYHoPS_6y4UmxFKCfGt1mq8uJ0iQqSm4H_J6AA6XM","summonerLevel":623,"summonerName":"","teamEarlySurrendered":false,"teamId":100,"teamPosition":"JUNGLE","timeCCingOthers":41,"timePlayed":2473,"totalAllyJungleMinionsKilled":144,"totalDamageDealt":315450,"totalDamageDealtToChampions":38023,"totalDamageShieldedOnTeammates":0,"totalDamageTaken":40865,"totalEnemyJungleMinionsKilled":8,"totalHeal":16558,"totalHealsOnTeammates":0,"totalMinionsKilled":13,"totalTimeCCDealt":752,"totalTimeSpentDead":317,"totalUnitsHealed":1,"tripleKills":0,"trueDamageDealt":90410,"trueDamageDealtToChampions":3097,"trueDamageTaken":615,"turretKills":1,"turretTakedowns":5,"turretsLost":5,"unrealKills":0,"visionClearedPings":0,"visionScore":35,"visionWardsBoughtInGame":3,"wardsKilled":2,"wardsPlaced":16,"win":true},{"PlayerScore0":0,"PlayerScore1":0,"PlayerScore10":0,"PlayerScore11":0,"PlayerScore2":0,"PlayerScore3":0,"PlayerScore4":0,"PlayerScore5":0,"PlayerScore6":0,"PlayerScore7":0,"PlayerScore8":0,"PlayerScore9":0,"allInPings":0,"assistMePings":0,"assists":10,"baronKills":0,"basicPings":0,"challenges":{"12AssistStreakCount":0,"HealFromMapSources":547.1816329956055,"InfernalScalePickup":0,"SWARM_DefeatAatrox":0,"SWARM_DefeatBriar":0,"SWARM_DefeatMiniBosses":0,"SWARM_EvolveWeapon":0,"SWARM_Have3Passives":0,"SWARM_KillEnemy":0,"SWARM_PickupGold":0,"SWARM_ReachLevel50":0,"SWARM_Survive15Min":0,"SWARM_WinWith5EvolvedWeapons":0,"abilityUses":860,"acesBefore15Minutes":0,"alliedJungleMonsterKills":2,"baronTakedowns":0,"blastConeOppositeOpponentCount":0,"bountyGold":0,"buffsStolen":0,"completeSupportQuestInTime":0,"controlWardsPlaced":0,"damagePerMinute":1331.321334099989,"damageTakenOnTeamPercentage":0.23090917232948183,"dancedWithRiftHerald":0,"deathsByEnemyChamps":16,"dodgeSkillShotsSmallWindow":0,"doubleAces":0,"dragonTakedowns":1,"earliestBaron":1771.7437100500001,"earliestDragonTakedown":2336.1324166120003,"earlyLaningPhaseGoldExpAdvantage":1,"effectiveHealAndShielding":0,"elderDragonKillsWithOpposingSoul":0,"elderDragonMultikills":0,"enemyChampionImmobilizations":23,"enemyJungleMonsterKills":14,"epicMonsterKillsNearEnemyJungler":0,"epicMonsterKillsWithin30SecondsOfSpawn":0,"epicMonsterSteals":0,"epicMonsterStolenWithoutSmite":0,"firstTurretKilled":1,"firstTurretKilledTime":890.0594295100001,"fistBumpParticipation":0,"flawlessAces":0,"fullTeamTakedown":2,"gameLength":2473.2871889460002,"getTakedownsInAllLanesEarlyJungleAsLaner":0,"goldPerMinute":406.7999423739655,"hadOpenNexus":0,"highestCrowdControlScore":1,"immobilizeAndKillWithAlly":3,"initialBuffCount":0,"initialCrabCount":0,"jungleCsBefore10Minutes":0,"junglerTakedownsNearDamagedEpicMonster":0,"kTurretsDestroyedBeforePlatesFall":0,"kda":1.375,"killAfterHiddenWithAlly":1,"killParticipation":0.4583333333333333,"killedChampTookFullTeamDamageSurvived":0,"killingSprees":1,"killsNearEnemyTurret":3,"killsOnOtherLanesEarlyJungleAsLaner":2,"killsOnRecentlyHealedByAramPack":0,"killsUnderOwnTurret":0,"killsWithHelpFromEpicMonster":1,"knockEnemyIntoTeamAndKill":0,"landSkillShotsEarlyGame":3,"laneMinionsFirst10Minutes":75,"laningPhaseGoldExpAdvantage":0,"legendaryCount":0,"legendaryItemUsed":[6657,3116,3003,3040,6653,8010],"lostAnInhibitor":0,"maxCsAdvantageOnLaneOpponent":37,"maxKillDeficit":2,"maxLevelLeadLaneOpponent":2,"mejaisFullStackInTime":0,"moreEnemyJungleThanOpponent":0,"multiKillOneSpell":0,"multiTurretRiftHeraldCount":0,"multikills":2,"multikillsAfterAggressiveFlash":1,"outerTurretExecutesBefore10Minutes":0,"outnumberedKills":5,"outnumberedNexusKill":0,"perfectDragonSoulsTaken":0,"perfectGame":0,"pickKillWithAlly":12,"playedChampSelectPosition":1,"poroExplosions":0,"quickCleanse":0,"quickFirstTurret":0,"quickSoloKills":0,"riftHeraldTakedowns":0,"saveAllyFromDeath":0,"scuttleCrabKills":0,"skillshotsDodged":34,"skillshotsHit":17,"snowballsHit":0,"soloBaronKills":0,"soloKills":4,"stealthWardsPlaced":13,"survivedSingleDigitHpCount":0,"survivedThreeImmobilizesInFight":0,"takedownOnFirstTurret":1,"takedowns":22,"takedownsAfterGainingLevelAdvantage":0,"takedownsBeforeJungleMinionSpawn":0,"takedownsFirstXMinutes":8,"takedownsInAlcove":0,"takedownsInEnemyFountain":0,"teamBaronKills":1,"teamDamagePercentage":0.25623576407713683,"teamElderDragonKills":0,"teamRiftHeraldKills":0,"tookLargeDamageSurvived":0,"turretPlatesTaken":4,"turretTakedowns":2,"turretsTakenWithRiftHerald":0,"twentyMinionsIn3SecondsCount":0,"twoWardsOneSweeperCount":0,"unseenRecalls":0,"visionScoreAdvantageLaneOpponent":-0.0021639466285705566,"visionScorePerMinute":0.5436490455843782,"voidMonsterKill":0,"wardTakedowns":0,"wardTakedownsBefore20M":0,"wardsGuarded":0},"champExperience":20626,"champLevel":18,"championId":69,"championName":"Cassiopeia","championTransform":0,"commandPings":5,"consumablesPurchased":2,"damageDealtToBuildings":4578,"damageDealtToObjectives":10948,"damageDealtToTurrets":4578,"damageSelfMitigated":34135,"dangerPings":0,"deaths":16,"detectorWardsPlaced":0,"doubleKills":2,"dragonKills":0,"eligibleForProgression":true,"enemyMissingPings":6,"enemyVisionPings":1,"firstBloodAssist":false,"firstBloodKill":false,"firstTowerAssist":false,"firstTowerKill":true,"gameEndedInEarlySurrender":false,"gameEndedInSurrender":false,"getBackPings":0,"goldEarned":16768,"goldSpent":16150,"holdPings":0,"individualPosition":"MIDDLE","inhibitorKills":0,"inhibitorTakedowns":3,"inhibitorsLost":0,"item0":6653,"item1":3116,"item2":3040,"item3":8010,"item4":3147,"item5":6657,"item6":3340,"itemsPurchased":27,"killingSprees":4,"kills":12,"lane":"MIDDLE","largestCriticalStrike":0,"largestKillingSpree":3,"largestMultiKill":2,"longestTimeSpentLiving":227,"magicDamageDealt":209205,"magicDamageDealtToChampions":51971,"magicDamageTaken":14996,"missions":{"playerScore0":0,"playerScore1":0,"playerScore2":0,"playerScore3":0,"playerScore4":0,"playerScore5":0,"playerScore6":0,"playerScore7":0,"playerScore8":0,"playerScore9":0,"playerScore10":0,"playerScore11":0},"needVisionPings":0,"neutralMinionsKilled":16,"nexusKills":0,"nexusLost":0,"nexusTakedowns":0,"objectivesStolen":0,"objectivesStolenAssists":0,"onMyWayPings":0,"participantId":3,"pentaKills":0,"perks":{"statPerks":{"defense":5001,"flex":5008,"offense":5008},"styles":[{"description":"primaryStyle","selections":[{"perk":8010,"var1":1182,"var2":0,"var3":0},{"perk":8009,"var1":5945,"var2":0,"var3":0},{"perk":9105,"var1":11,"var2":0,"var3":0},{"perk":8299,"var1":2983,"var2":0,"var3":0}],"style":8000},{"description":"subStyle","selections":[{"perk":8226,"var1":250,"var2":1050,"var3":0},{"perk":8210,"var1":14,"var2":0,"var3":0}],"style":8200}]},"physicalDamageDealt":12313,"physicalDamageDealtToChampions":651,"physicalDamageTaken":46960,"placement":0,"playerAugment1":0,"playerAugment2":0,"playerAugment3":0,"playerAugment4":0,"playerAugment5":0,"playerAugment6":0,"playerSubteamId":0,"profileIcon":6874,"pushPings":0,"puuid":"9CTD4yr8UZ5AgCgXsEZhCQViAluBxZ7F69tEBoFq7jA0XITiUSZA1KZRJFr7nlZX3Nmjl1hLsbEdeQ","quadraKills":0,"retreatPings":3,"riotIdGameName":"Spitchy","riotIdTagline":"6969","role":"SOLO","sightWardsBoughtInGame":0,"spell1Casts":202,"spell2Casts":39,"spell3Casts":604,"spell4Casts":15,"subteamPlacement":0,"summoner1Casts":6,"summoner1Id":4,"summoner2Casts":5,"summoner2Id":12,"summonerId":"jg7ven-B6dZX2P5yjpsuNWufN5PFGt14oLnH4MHsKfVB8KM","summonerLevel":967,"summonerName":"","teamEarlySurrendered":false,"teamId":100,"teamPosition":"MIDDLE","timeCCingOthers":84,"timePlayed":2473,"totalAllyJungleMinionsKilled":2,"totalDamageDealt":230484,"totalDamageDealtToChampions":54879,"totalDamageShieldedOnTeammates":0,"totalDamageTaken":65864,"totalEnemyJungleMinionsKilled":10,"totalHeal":15271,"totalHealsOnTeammates":0,"totalMinionsKilled":204,"totalTimeCCDealt":995,"totalTimeSpentDead":606,"totalUnitsHealed":1,"tripleKills":0,"trueDamageDealt":8966,"trueDamageDealtToChampions":2256,"trueDamageTaken":3907,"turretKills":2,"turretTakedowns":2,"turretsLost":5,"unrealKills":0,"visionClearedPings":0,"visionScore":22,"visionWardsBoughtInGame":0,"wardsKilled":0,"wardsPlaced":13,"win":true},{"PlayerScore0":0,"PlayerScore1":0,"PlayerScore10":0,"PlayerScore11":0,"PlayerScore2":0,"PlayerScore3":0,"PlayerScore4":0,"PlayerScore5":0,"PlayerScore6":0,"PlayerScore7":0,"PlayerScore8":0,"PlayerScore9":0,"allInPings":0,"assistMePings":2,"assists":16,"baronKills":0,"basicPings":0,"challenges":{"12AssistStreakCount":0,"HealFromMapSources":646,"InfernalScalePickup":0,"SWARM_DefeatAatrox":0,"SWARM_DefeatBriar":0,"SWARM_DefeatMiniBosses":0,"SWARM_EvolveWeapon":0,"SWARM_Have3Passives":0,"SWARM_KillEnemy":0,"SWARM_PickupGold":0,"SWARM_ReachLevel50":0,"SWARM_Survive15Min":0,"SWARM_WinWith5EvolvedWeapons":0,"abilityUses":213,"acesBefore15Minutes":0,"alliedJungleMonsterKills":28,"baronTakedowns":1,"blastConeOppositeOpponentCount":0,"bountyGold":395.3417663574219,"buffsStolen":0,"completeSupportQuestInTime":0,"controlWardsPlaced":1,"damagePerMinute":1200.0334125734244,"damageTakenOnTeamPercentage":0.12786337867556885,"dancedWithRiftHerald":0,"deathsByEnemyChamps":6,"dodgeSkillShotsSmallWindow":0,"doubleAces":0,"dragonTakedowns":3,"earliestBaron":1771.7437100500001,"earliestDragonTakedown":918.484371816,"earlyLaningPhaseGoldExpAdvantage":1,"effectiveHealAndShielding":0,"elderDragonKillsWithOpposingSoul":0,"elderDragonMultikills":0,"enemyChampionImmobilizations":15,"enemyJungleMonsterKills":3,"epicMonsterKillsNearEnemyJungler":0,"epicMonsterKillsWithin30SecondsOfSpawn":0,"epicMonsterSteals":0,"epicMonsterStolenWithoutSmite":0,"firstTurretKilled":1,"firstTurretKilledTime":890.0594295100001,"fistBumpParticipation":0,"flawlessAces":0,"fullTeamTakedown":2,"gameLength":2473.2871889460002,"getTakedownsInAllLanesEarlyJungleAsLaner":0,"goldPerMinute":469.7843921817881,"hadOpenNexus":0,"immobilizeAndKillWithAlly":6,"initialBuffCount":0,"initialCrabCount":0,"jungleCsBefore10Minutes":0,"junglerTakedownsNearDamagedEpicMonster":0,"kTurretsDestroyedBeforePlatesFall":0,"kda":5.166666666666667,"killAfterHiddenWithAlly":8,"killParticipation":0.6458333333333334,"killedChampTookFullTeamDamageSurvived":0,"killingSprees":2,"killsNearEnemyTurret":2,"killsOnOtherLanesEarlyJungleAsLaner":0,"killsOnRecentlyHealedByAramPack":0,"killsUnderOwnTurret":0,"killsWithHelpFromEpicMonster":0,"knockEnemyIntoTeamAndKill":0,"landSkillShotsEarlyGame":10,"laneMinionsFirst10Minutes":51,"laningPhaseGoldExpAdvantage":0,"legendaryCount":0,"legendaryItemUsed":[3032,3085,3031,3033,3026],"lostAnInhibitor":0,"maxCsAdvantageOnLaneOpponent":70.2000000178814,"maxKillDeficit":2,"maxLevelLeadLaneOpponent":2,"mejaisFullStackInTime":0,"moreEnemyJungleThanOpponent":0,"multiKillOneSpell":0,"multiTurretRiftHeraldCount":0,"multikills":3,"multikillsAfterAggressiveFlash":1,"outerTurretExecutesBefore10Minutes":0,"outnumberedKills":0,"outnumberedNexusKill":0,"perfectDragonSoulsTaken":0,"perfectGame":0,"pickKillWithAlly":25,"playedChampSelectPosition":1,"poroExplosions":0,"quickCleanse":0,"quickFirstTurret":0,"quickSoloKills":0,"riftHeraldTakedowns":0,"saveAllyFromDeath":0,"scuttleCrabKills":0,"skillshotsDodged":19,"skillshotsHit":83,"snowballsHit":0,"soloBaronKills":0,"soloKills":0,"stealthWardsPlaced":6,"survivedSingleDigitHpCount":0,"survivedThreeImmobilizesInFight":2,"takedownOnFirstTurret":0,"takedowns":31,"takedownsAfterGainingLevelAdvantage":0,"takedownsBeforeJungleMinionSpawn":0,"takedownsFirstXMinutes":7,"takedownsInAlcove":0,"takedownsInEnemyFountain":0,"teamBaronKills":1,"teamDamagePercentage":0.23096713807017774,"teamElderDragonKills":0,"teamRiftHeraldKills":0,"tookLargeDamageSurvived":0,"turretPlatesTaken":1,"turretTakedowns":4,"turretsTakenWithRiftHerald":0,"twentyMinionsIn3SecondsCount":0,"twoWardsOneSweeperCount":0,"unseenRecalls":0,"visionScoreAdvantageLaneOpponent":0.6988236904144287,"visionScorePerMinute":0.9863336843198129,"voidMonsterKill":1,"wardTakedowns":2,"wardTakedownsBefore20M":1,"wardsGuarded":0},"champExperience":19934,"champLevel":18,"championId":22,"championName":"Ashe","championTransform":0,"commandPings":7,"consumablesPurchased":3,"damageDealtToBuildings":4545,"damageDealtToObjectives":29540,"damageDealtToTurrets":4545,"damageSelfMitigated":21090,"dangerPings":0,"deaths":6,"detectorWardsPlaced":1,"doubleKills":3,"dragonKills":0,"eligibleForProgression":true,"enemyMissingPings":13,"enemyVisionPings":15,"firstBloodAssist":false,"firstBloodKill":true,"firstTowerAssist":true,"firstTowerKill":false,"gameEndedInEarlySurrender":false,"gameEndedInSurrender":false,"getBackPings":7,"goldEarned":19365,"goldSpent":18375,"holdPings":0,"individualPosition":"BOTTOM","inhibitorKills":1,"inhibitorTakedowns":1,"inhibitorsLost":0,"item0":3172,"item1":3032,"item2":3026,"item3":3031,"item4":3085,"item5":3033,"item6":3363,"itemsPurchased":30,"killingSprees":3,"kills":15,"lane":"BOTTOM","largestCriticalStrike":674,"largestKillingSpree":7,"largestMultiKill":2,"longestTimeSpentLiving":828,"magicDamageDealt":4240,"magicDamageDealtToChampions":4117,"magicDamageTaken":10626,"missions":{"playerScore0":0,"playerScore1":0,"playerScore2":0,"playerScore3":0,"playerScore4":0,"playerScore5":0,"playerScore6":0,"playerScore7":0,"playerScore8":0,"playerScore9":0,"playerScore10":0,"playerScore11":0},"needVisionPings":0,"neutralMinionsKilled":35,"nexusKills":0,"nexusLost":0,"nexusTakedowns":1,"objectivesStolen":0,"objectivesStolenAssists":0,"onMyWayPings":14,"participantId":4,"pentaKills":0,"perks":{"statPerks":{"defense":5011,"flex":5008,"offense":5005},"styles":[{"description":"primaryStyle","selections":[{"perk":8008,"var1":1096,"var2":1096,"var3":0},{"perk":8009,"var1":3064,"var2":0,"var3":0},{"perk":9103,"var1":18,"var2":0,"var3":0},{"perk":8017,"var1":1985,"var2":0,"var3":0}],"style":8000},{"description":"subStyle","selections":[{"perk":8345,"var1":3,"var2":0,"var3":187},{"perk":8410,"var1":201,"var2":0,"var3":0}],"style":8300}]},"physicalDamageDealt":256376,"physicalDamageDealtToChampions":43513,"physicalDamageTaken":23494,"placement":0,"playerAugment1":0,"playerAugment2":0,"playerAugment3":0,"playerAugment4":0,"playerAugment5":0,"playerAugment6":0,"playerSubteamId":0,"profileIcon":29,"pushPings":0,"puuid":"gQvdGllqhzI-EKGDsKPwZ1agj7t6N7sf4Ot8vwXKPYyxz7PRS9vNZyM2E1RtyZnq7j7u1FRwRZzhiA","quadraKills":0,"retreatPings":0,"riotIdGameName":"Pidgey","riotIdTagline":"NA2","role":"CARRY","sightWardsBoughtInGame":0,"spell1Casts":39,"spell2Casts":136,"spell3Casts":21,"spell4Casts":17,"subteamPlacement":0,"summoner1Casts":8,"summoner1Id":21,"summoner2Casts":6,"summoner2Id":4,"summonerId":"saZakE38OUfNj7QSeOI01x-4o2BlfvXMXeYn4duHSEcGaoQ","summonerLevel":99,"summonerName":"","teamEarlySurrendered":false,"teamId":100,"teamPosition":"BOTTOM","timeCCingOthers":65,"timePlayed":2473,"totalAllyJungleMinionsKilled":31,"totalDamageDealt":267134,"totalDamageDealtToChampions":49467,"totalDamageShieldedOnTeammates":0,"totalDamageTaken":36471,"totalEnemyJungleMinionsKilled":4,"totalHeal":13772,"totalHealsOnTeammates":0,"totalMinionsKilled":215,"totalTimeCCDealt":881,"totalTimeSpentDead":254,"totalUnitsHealed":1,"tripleKills":0,"trueDamageDealt":6517,"trueDamageDealtToChampions":1836,"trueDamageTaken":2350,"turretKills":1,"turretTakedowns":4,"turretsLost":5,"unrealKills":0,"visionClearedPings":0,"visionScore":40,"visionWardsBoughtInGame":2,"wardsKilled":1,"wardsPlaced":16,"win":true},{"PlayerScore0":0,"PlayerScore1":0,"PlayerScore10":0,"PlayerScore11":0,"PlayerScore2":0,"PlayerScore3":0,"PlayerScore4":0,"PlayerScore5":0,"PlayerScore6":0,"PlayerScore7":0,"PlayerScore8":0,"PlayerScore9":0,"allInPings":0,"assistMePings":2,"assists":30,"baronKills":0,"basicPings":0,"challenges":{"12AssistStreakCount":1,"HealFromMapSources":1406.3096733093262,"InfernalScalePickup":0,"SWARM_DefeatAatrox":0,"SWARM_DefeatBriar":0,"SWARM_DefeatMiniBosses":0,"SWARM_EvolveWeapon":0,"SWARM_Have3Passives":0,"SWARM_KillEnemy":0,"SWARM_PickupGold":0,"SWARM_ReachLevel50":0,"SWARM_Survive15Min":0,"SWARM_WinWith5EvolvedWeapons":0,"abilityUses":180,"acesBefore15Minutes":0,"alliedJungleMonsterKills":0,"baronTakedowns":1,"blastConeOppositeOpponentCount":0,"bountyGold":0,"buffsStolen":0,"completeSupportQuestInTime":0,"controlWardTimeCoverageInRiverOrEnemyHalf":0.302920726081664,"controlWardsPlaced":2,"damagePerMinute":544.760758358061,"damageTakenOnTeamPercentage":0.14188436339942284,"dancedWithRiftHerald":0,"deathsByEnemyChamps":6,"dodgeSkillShotsSmallWindow":0,"doubleAces":0,"dragonTakedowns":2,"earliestBaron":1771.7437100500001,"earliestDragonTakedown":1232.880148016,"earlyLaningPhaseGoldExpAdvantage":0,"effectiveHealAndShielding":439.9997863769531,"elderDragonKillsWithOpposingSoul":0,"elderDragonMultikills":0,"enemyChampionImmobilizations":90,"enemyJungleMonsterKills":0,"epicMonsterKillsNearEnemyJungler":0,"epicMonsterKillsWithin30SecondsOfSpawn":0,"epicMonsterSteals":0,"epicMonsterStolenWithoutSmite":0,"firstTurretKilled":1,"firstTurretKilledTime":890.0594295100001,"fistBumpParticipation":0,"flawlessAces":0,"fullTeamTakedown":2,"gameLength":2473.2871889460002,"getTakedownsInAllLanesEarlyJungleAsLaner":0,"goldPerMinute":300.8971547870046,"hadOpenNexus":0,"immobilizeAndKillWithAlly":24,"initialBuffCount":0,"initialCrabCount":0,"jungleCsBefore10Minutes":0,"junglerTakedownsNearDamagedEpicMonster":0,"kTurretsDestroyedBeforePlatesFall":0,"kda":5.666666666666667,"killAfterHiddenWithAlly":1,"killParticipation":0.7083333333333334,"killedChampTookFullTeamDamageSurvived":0,"killingSprees":1,"killsNearEnemyTurret":0,"killsOnOtherLanesEarlyJungleAsLaner":2,"killsOnRecentlyHealedByAramPack":0,"killsUnderOwnTurret":1,"killsWithHelpFromEpicMonster":0,"knockEnemyIntoTeamAndKill":0,"landSkillShotsEarlyGame":4,"laneMinionsFirst10Minutes":10,"laningPhaseGoldExpAdvantage":0,"legendaryCount":0,"legendaryItemUsed":[3075,3876,3109,3068],"lostAnInhibitor":0,"maxCsAdvantageOnLaneOpponent":7,"maxKillDeficit":2,"maxLevelLeadLaneOpponent":1,"mejaisFullStackInTime":0,"moreEnemyJungleThanOpponent":0,"multiKillOneSpell":0,"multiTurretRiftHeraldCount":0,"multikills":0,"multikillsAfterAggressiveFlash":0,"outerTurretExecutesBefore10Minutes":0,"outnumberedKills":0,"outnumberedNexusKill":0,"perfectDragonSoulsTaken":0,"perfectGame":0,"pickKillWithAlly":25,"playedChampSelectPosition":1,"poroExplosions":0,"quickCleanse":0,"quickFirstTurret":0,"quickSoloKills":0,"riftHeraldTakedowns":0,"saveAllyFromDeath":1,"scuttleCrabKills":0,"skillshotsDodged":34,"skillshotsHit":35,"snowballsHit":0,"soloBaronKills":0,"soloKills":0,"stealthWardsPlaced":37,"survivedSingleDigitHpCount":0,"survivedThreeImmobilizesInFight":7,"takedownOnFirstTurret":0,"takedowns":34,"takedownsAfterGainingLevelAdvantage":0,"takedownsBeforeJungleMinionSpawn":0,"takedownsFirstXMinutes":11,"takedownsInAlcove":0,"takedownsInEnemyFountain":0,"teamBaronKills":1,"teamDamagePercentage":0.1048486083575632,"teamElderDragonKills":0,"teamRiftHeraldKills":0,"tookLargeDamageSurvived":1,"turretPlatesTaken":1,"turretTakedowns":2,"turretsTakenWithRiftHerald":0,"twentyMinionsIn3SecondsCount":0,"twoWardsOneSweeperCount":2,"unseenRecalls":0,"visionScoreAdvantageLaneOpponent":0.23339664936065674,"visionScorePerMinute":2.216077007774669,"voidMonsterKill":1,"wardTakedowns":7,"wardTakedownsBefore20M":5,"wardsGuarded":3},"champExperience":15949,"champLevel":16,"championId":89,"championName":"Leona","championTransform":0,"commandPings":4,"consumablesPurchased":4,"damageDealtToBuildings":1312,"damageDealtToObjectives":4161,"damageDealtToTurrets":1312,"damageSelfMitigated":76239,"dangerPings":0,"deaths":6,"detectorWardsPlaced":2,"doubleKills":0,"dragonKills":1,"eligibleForProgression":true,"enemyMissingPings":0,"enemyVisionPings":0,"firstBloodAssist":true,"firstBloodKill":false,"firstTowerAssist":false,"firstTowerKill":false,"gameEndedInEarlySurrender":false,"gameEndedInSurrender":false,"getBackPings":0,"goldEarned":12403,"goldSpent":10700,"holdPings":0,"individualPosition":"UTILITY","inhibitorKills":0,"inhibitorTakedowns":1,"inhibitorsLost":0,"item0":3876,"item1":3174,"item2":3075,"item3":3109,"item4":3068,"item5":1011,"item6":3364,"itemsPurchased":25,"killingSprees":1,"kills":4,"lane":"BOTTOM","largestCriticalStrike":41,"largestKillingSpree":3,"largestMultiKill":1,"longestTimeSpentLiving":926,"magicDamageDealt":27356,"magicDamageDealtToChampions":15077,"magicDamageTaken":9523,"missions":{"playerScore0":0,"playerScore1":0,"playerScore2":0,"playerScore3":0,"playerScore4":0,"playerScore5":0,"playerScore6":0,"playerScore7":0,"playerScore8":0,"playerScore9":0,"playerScore10":0,"playerScore11":0},"needVisionPings":0,"neutralMinionsKilled":4,"nexusKills":0,"nexusLost":0,"nexusTakedowns":1,"objectivesStolen":0,"objectivesStolenAssists":0,"onMyWayPings":3,"participantId":5,"pentaKills":0,"perks":{"statPerks":{"defense":5001,"flex":5001,"offense":5007},"styles":[{"description":"primaryStyle","selections":[{"perk":8439,"var1":1596,"var2":1373,"var3":0},{"perk":8463,"var1":1574,"var2":0,"var3":0},{"perk":8473,"var1":786,"var2":0,"var3":0},{"perk":8242,"var1":234,"var2":0,"var3":0}],"style":8400},{"description":"subStyle","selections":[{"perk":8345,"var1":3,"var2":0,"var3":223},{"perk":8347,"var1":0,"var2":0,"var3":0}],"style":8300}]},"physicalDamageDealt":12723,"physicalDamageDealtToChampions":5098,"physicalDamageTaken":27394,"placement":0,"playerAugment1":0,"playerAugment2":0,"playerAugment3":0,"playerAugment4":0,"playerAugment5":0,"playerAugment6":0,"playerSubteamId":0,"profileIcon":5634,"pushPings":0,"puuid":"7OBszlEcstXuVag_dgSSCJ-PySoaTp3XyvyswcClR0Xpe6wbVprvjlTIokEu8MOU0WXUCWzEUV7OPg","quadraKills":0,"retreatPings":1,"riotIdGameName":"AlwaysJustinTime","riotIdTagline":"NA1","role":"SUPPORT","sightWardsBoughtInGame":0,"spell1Casts":76,"spell2Casts":47,"spell3Casts":46,"spell4Casts":11,"subteamPlacement":0,"summoner1Casts":8,"summoner1Id":14,"summoner2Casts":3,"summoner2Id":4,"summonerId":"XTnDo-_oGKkmT1iH6hnuW6Yztr1wC0HMYBYzdzGNHKhu0dg","summonerLevel":540,"summonerName":"","teamEarlySurrendered":false,"teamId":100,"teamPosition":"UTILITY","timeCCingOthers":73,"timePlayed":2473,"totalAllyJungleMinionsKilled":0,"totalDamageDealt":46030,"totalDamageDealtToChampions":22455,"totalDamageShieldedOnTeammates":0,"totalDamageTaken":40471,"totalEnemyJungleMinionsKilled":0,"totalHeal":9598,"totalHealsOnTeammates":439,"totalMinionsKilled":36,"totalTimeCCDealt":129,"totalTimeSpentDead":235,"totalUnitsHealed":5,"tripleKills":0,"trueDamageDealt":5950,"trueDamageDealtToChampions":2279,"trueDamageTaken":3552,"turretKills":0,"turretTakedowns":2,"turretsLost":5,"unrealKills":0,"visionClearedPings":0,"visionScore":91,"visionWardsBoughtInGame":2,"wardsKilled":5,"wardsPlaced":39,"win":true},{"PlayerScore0":0,"PlayerScore1":0,"PlayerScore10":0,"PlayerScore11":0,"PlayerScore2":0,"PlayerScore3":0,"PlayerScore4":0,"PlayerScore5":0,"PlayerScore6":0,"PlayerScore7":0,"PlayerScore8":0,"PlayerScore9":0,"allInPings":2,"assistMePings":7,"assists":9,"baronKills":0,"basicPings":0,"challenges":{"12AssistStreakCount":0,"HealFromMapSources":0,"InfernalScalePickup":0,"SWARM_DefeatAatrox":0,"SWARM_DefeatBriar":0,"SWARM_DefeatMiniBosses":0,"SWARM_EvolveWeapon":0,"SWARM_Have3Passives":0,"SWARM_KillEnemy":0,"SWARM_PickupGold":0,"SWARM_ReachLevel50":0,"SWARM_Survive15Min":0,"SWARM_WinWith5EvolvedWeapons":0,"abilityUses":229,"acesBefore15Minutes":0,"alliedJungleMonsterKills":0,"baronTakedowns":0,"blastConeOppositeOpponentCount":0,"bountyGold":133.8201904296875,"buffsStolen":0,"completeSupportQuestInTime":0,"controlWardsPlaced":1,"damagePerMinute":1452.2002528871785,"damageTakenOnTeamPercentage":0.21480515856515026,"dancedWithRiftHerald":0,"deathsByEnemyChamps":9,"dodgeSkillShotsSmallWindow":7,"doubleAces":0,"dragonTakedowns":0,"earliestBaron":2192.954524992,"earlyLaningPhaseGoldExpAdvantage":0,"effectiveHealAndShielding":0,"elderDragonKillsWithOpposingSoul":0,"elderDragonMultikills":0,"enemyChampionImmobilizations":0,"enemyJungleMonsterKills":0,"epicMonsterKillsNearEnemyJungler":0,"epicMonsterKillsWithin30SecondsOfSpawn":0,"epicMonsterSteals":0,"epicMonsterStolenWithoutSmite":0,"firstTurretKilled":0,"fistBumpParticipation":0,"flawlessAces":1,"fullTeamTakedown":2,"gameLength":2473.2871889460002,"getTakedownsInAllLanesEarlyJungleAsLaner":0,"goldPerMinute":401.99420181313513,"hadOpenNexus":0,"highestChampionDamage":1,"immobilizeAndKillWithAlly":0,"initialBuffCount":0,"initialCrabCount":0,"jungleCsBefore10Minutes":0,"junglerTakedownsNearDamagedEpicMonster":0,"kTurretsDestroyedBeforePlatesFall":0,"kda":1.8888888888888888,"killAfterHiddenWithAlly":0,"killParticipation":0.38636363636363635,"killedChampTookFullTeamDamageSurvived":0,"killingSprees":1,"killsNearEnemyTurret":1,"killsOnOtherLanesEarlyJungleAsLaner":0,"killsOnRecentlyHealedByAramPack":0,"killsUnderOwnTurret":1,"killsWithHelpFromEpicMonster":0,"knockEnemyIntoTeamAndKill":0,"landSkillShotsEarlyGame":0,"laneMinionsFirst10Minutes":72,"laningPhaseGoldExpAdvantage":0,"legendaryCount":0,"legendaryItemUsed":[6631,3033,3161,4401],"lostAnInhibitor":0,"maxCsAdvantageOnLaneOpponent":42,"maxKillDeficit":0,"maxLevelLeadLaneOpponent":3,"mejaisFullStackInTime":0,"moreEnemyJungleThanOpponent":0,"multiKillOneSpell":0,"multiTurretRiftHeraldCount":0,"multikills":0,"multikillsAfterAggressiveFlash":0,"outerTurretExecutesBefore10Minutes":0,"outnumberedKills":2,"outnumberedNexusKill":0,"perfectDragonSoulsTaken":0,"perfectGame":0,"pickKillWithAlly":9,"playedChampSelectPosition":1,"poroExplosions":0,"quickCleanse":0,"quickFirstTurret":0,"quickSoloKills":0,"riftHeraldTakedowns":0,"saveAllyFromDeath":0,"scuttleCrabKills":0,"skillshotsDodged":88,"skillshotsHit":0,"snowballsHit":0,"soloBaronKills":0,"soloKills":4,"stealthWardsPlaced":7,"survivedSingleDigitHpCount":0,"survivedThreeImmobilizesInFight":2,"takedownOnFirstTurret":0,"takedowns":17,"takedownsAfterGainingLevelAdvantage":0,"takedownsBeforeJungleMinionSpawn":0,"takedownsFirstXMinutes":3,"takedownsInAlcove":0,"takedownsInEnemyFountain":0,"teamBaronKills":1,"teamDamagePercentage":0.2457029226558465,"teamElderDragonKills":0,"teamRiftHeraldKills":1,"teleportTakedowns":1,"tookLargeDamageSurvived":0,"turretPlatesTaken":0,"turretTakedowns":0,"turretsTakenWithRiftHerald":5,"twentyMinionsIn3SecondsCount":0,"twoWardsOneSweeperCount":0,"unseenRecalls":0,"visionScoreAdvantageLaneOpponent":0.17388808727264404,"visionScorePerMinute":0.4535684969811887,"voidMonsterKill":0,"wardTakedowns":2,"wardTakedownsBefore20M":1,"wardsGuarded":1},"champExperience":25607,"champLevel":18,"championId":86,"championName":"Garen","championTransform":0,"commandPings":22,"consumablesPurchased":2,"damageDealtToBuildings":466,"damageDealtToObjectives":466,"damageDealtToTurrets":466,"damageSelfMitigated":76644,"dangerPings":0,"deaths":9,"detectorWardsPlaced":1,"doubleKills":0,"dragonKills":0,"eligibleForProgression":true,"enemyMissingPings":2,"enemyVisionPings":2,"firstBloodAssist":false,"firstBloodKill":false,"firstTowerAssist":false,"firstTowerKill":false,"gameEndedInEarlySurrender":false,"gameEndedInSurrender":false,"getBackPings":0,"goldEarned":16570,"goldSpent":15285,"holdPings":0,"individualPosition":"TOP","inhibitorKills":0,"inhibitorTakedowns":0,"inhibitorsLost":4,"item0":6631,"item1":4401,"item2":3033,"item3":3047,"item4":3161,"item5":3066,"item6":3364,"itemsPurchased":25,"killingSprees":1,"kills":8,"lane":"TOP","largestCriticalStrike":915,"largestKillingSpree":4,"largestMultiKill":1,"longestTimeSpentLiving":760,"magicDamageDealt":0,"magicDamageDealtToChampions":0,"magicDamageTaken":21854,"missions":{"playerScore0":0,"playerScore1":0,"playerScore2":0,"playerScore3":0,"playerScore4":0,"playerScore5":0,"playerScore6":0,"playerScore7":0,"playerScore8":0,"playerScore9":0,"playerScore10":0,"playerScore11":0},"needVisionPings":0,"neutralMinionsKilled":0,"nexusKills":0,"nexusLost":1,"nexusTakedowns":0,"objectivesStolen":0,"objectivesStolenAssists":0,"onMyWayPings":22,"participantId":6,"pentaKills":0,"perks":{"statPerks":{"defense":5001,"flex":5008,"offense":5008},"styles":[{"description":"primaryStyle","selections":[{"perk":8010,"var1":2710,"var2":0,"var3":0},{"perk":9111,"var1":1848,"var2":340,"var3":0},{"perk":9105,"var1":18,"var2":40,"var3":0},{"perk":8299,"var1":2173,"var2":0,"var3":0}],"style":8000},{"description":"subStyle","selections":[{"perk":8224,"var1":76,"var2":1455,"var3":0},{"perk":8234,"var1":15622,"var2":0,"var3":0}],"style":8200}]},"physicalDamageDealt":260005,"physicalDamageDealtToChampions":46505,"physicalDamageTaken":33232,"placement":0,"playerAugment1":0,"playerAugment2":0,"playerAugment3":0,"playerAugment4":0,"playerAugment5":0,"playerAugment6":0,"playerSubteamId":0,"profileIcon":3500,"pushPings":0,"puuid":"il8KkxRNM60ai0qKMaEBTWD8M0E-NQ23cNsgEVlUxjewEDviO07l3bNpPGuLWtdZLFu9Qaux1Zjnhw","quadraKills":0,"retreatPings":1,"riotIdGameName":"I am VayNese","riotIdTagline":"NA1","role":"SOLO","sightWardsBoughtInGame":0,"spell1Casts":123,"spell2Casts":23,"spell3Casts":73,"spell4Casts":10,"subteamPlacement":0,"summoner1Casts":6,"summoner1Id":4,"summoner2Casts":4,"summoner2Id":12,"summonerId":"YyuurSMpPh3Yos2A3W9QcGR5iUe-9n56rs8San0F_b0GxRs","summonerLevel":799,"summonerName":"","teamEarlySurrendered":false,"teamId":200,"teamPosition":"TOP","timeCCingOthers":68,"timePlayed":2473,"totalAllyJungleMinionsKilled":0,"totalDamageDealt":276400,"totalDamageDealtToChampions":59861,"totalDamageShieldedOnTeammates":0,"totalDamageTaken":56118,"totalEnemyJungleMinionsKilled":0,"totalHeal":6857,"totalHealsOnTeammates":0,"totalMinionsKilled":303,"totalTimeCCDealt":356,"totalTimeSpentDead":360,"totalUnitsHealed":1,"tripleKills":0,"trueDamageDealt":16395,"trueDamageDealtToChampions":13356,"trueDamageTaken":1031,"turretKills":0,"turretTakedowns":0,"turretsLost":12,"unrealKills":0,"visionClearedPings":0,"visionScore":18,"visionWardsBoughtInGame":1,"wardsKilled":2,"wardsPlaced":8,"win":false},{"PlayerScore0":0,"PlayerScore1":0,"PlayerScore10":0,"PlayerScore11":0,"PlayerScore2":0,"PlayerScore3":0,"PlayerScore4":0,"PlayerScore5":0,"PlayerScore6":0,"PlayerScore7":0,"PlayerScore8":0,"PlayerScore9":0,"allInPings":0,"assistMePings":9,"assists":16,"baronKills":1,"basicPings":0,"challenges":{"12AssistStreakCount":0,"HealFromMapSources":214.99066162109375,"InfernalScalePickup":0,"SWARM_DefeatAatrox":0,"SWARM_DefeatBriar":0,"SWARM_DefeatMiniBosses":0,"SWARM_EvolveWeapon":0,"SWARM_Have3Passives":0,"SWARM_KillEnemy":0,"SWARM_PickupGold":0,"SWARM_ReachLevel50":0,"SWARM_Survive15Min":0,"SWARM_WinWith5EvolvedWeapons":0,"abilityUses":461,"acesBefore15Minutes":0,"alliedJungleMonsterKills":101,"baronTakedowns":1,"blastConeOppositeOpponentCount":0,"bountyGold":700,"buffsStolen":2,"completeSupportQuestInTime":0,"controlWardTimeCoverageInRiverOrEnemyHalf":0.4802612656382195,"controlWardsPlaced":3,"damagePerMinute":1383.5195788396209,"damageTakenOnTeamPercentage":0.29736580412599056,"dancedWithRiftHerald":0,"deathsByEnemyChamps":10,"dodgeSkillShotsSmallWindow":19,"doubleAces":0,"dragonTakedowns":2,"earliestBaron":2192.954524992,"earliestDragonTakedown":596.9472779040001,"earlyLaningPhaseGoldExpAdvantage":0,"effectiveHealAndShielding":0,"elderDragonKillsWithOpposingSoul":0,"elderDragonMultikills":0,"enemyChampionImmobilizations":33,"enemyJungleMonsterKills":8,"epicMonsterKillsNearEnemyJungler":0,"epicMonsterKillsWithin30SecondsOfSpawn":0,"epicMonsterSteals":0,"epicMonsterStolenWithoutSmite":0,"firstTurretKilled":0,"fistBumpParticipation":0,"flawlessAces":1,"fullTeamTakedown":2,"gameLength":2473.2871889460002,"goldPerMinute":459.00908480680545,"hadOpenNexus":0,"immobilizeAndKillWithAlly":9,"initialBuffCount":2,"initialCrabCount":1,"jungleCsBefore10Minutes":64.00000008940697,"junglerKillsEarlyJungle":0,"junglerTakedownsNearDamagedEpicMonster":0,"kTurretsDestroyedBeforePlatesFall":0,"kda":2.4,"killAfterHiddenWithAlly":0,"killParticipation":0.5454545454545454,"killedChampTookFullTeamDamageSurvived":0,"killingSprees":0,"killsNearEnemyTurret":1,"killsOnLanersEarlyJungleAsJungler":0,"killsOnRecentlyHealedByAramPack":0,"killsUnderOwnTurret":0,"killsWithHelpFromEpicMonster":0,"knockEnemyIntoTeamAndKill":0,"landSkillShotsEarlyGame":0,"laneMinionsFirst10Minutes":8,"laningPhaseGoldExpAdvantage":0,"legendaryCount":0,"legendaryItemUsed":[6699,3071,2501,6333,3065],"lostAnInhibitor":0,"maxCsAdvantageOnLaneOpponent":89.1000000834465,"maxKillDeficit":0,"maxLevelLeadLaneOpponent":2,"mejaisFullStackInTime":0,"moreEnemyJungleThanOpponent":-47.000000059604645,"multiKillOneSpell":1,"multiTurretRiftHeraldCount":0,"multikills":1,"multikillsAfterAggressiveFlash":0,"outerTurretExecutesBefore10Minutes":0,"outnumberedKills":1,"outnumberedNexusKill":0,"perfectDragonSoulsTaken":0,"perfectGame":0,"pickKillWithAlly":18,"playedChampSelectPosition":1,"poroExplosions":0,"quickCleanse":0,"quickFirstTurret":0,"quickSoloKills":0,"riftHeraldTakedowns":1,"saveAllyFromDeath":0,"scuttleCrabKills":6,"shortestTimeToAceFromFirstTakedown":57.66259511199996,"skillshotsDodged":136,"skillshotsHit":0,"snowballsHit":0,"soloBaronKills":0,"soloKills":1,"soloTurretsLategame":1,"stealthWardsPlaced":1,"survivedSingleDigitHpCount":0,"survivedThreeImmobilizesInFight":2,"takedownOnFirstTurret":0,"takedowns":24,"takedownsAfterGainingLevelAdvantage":0,"takedownsBeforeJungleMinionSpawn":0,"takedownsFirstXMinutes":5,"takedownsInAlcove":0,"takedownsInEnemyFountain":0,"teamBaronKills":1,"teamDamagePercentage":0.23408259528714617,"teamElderDragonKills":0,"teamRiftHeraldKills":1,"tookLargeDamageSurvived":0,"turretPlatesTaken":0,"turretTakedowns":2,"turretsTakenWithRiftHerald":5,"twentyMinionsIn3SecondsCount":0,"twoWardsOneSweeperCount":0,"unseenRecalls":0,"visionScoreAdvantageLaneOpponent":0.049529194831848145,"visionScorePerMinute":0.9031912072521563,"voidMonsterKill":2,"wardTakedowns":6,"wardTakedownsBefore20M":1,"wardsGuarded":0},"champExperience":24968,"champLevel":18,"championId":141,"championName":"Kayn","championTransform":1,"commandPings":17,"consumablesPurchased":4,"damageDealtToBuildings":3459,"damageDealtToObjectives":43684,"damageDealtToTurrets":3459,"damageSelfMitigated":94254,"dangerPings":0,"deaths":10,"detectorWardsPlaced":3,"doubleKills":1,"dragonKills":2,"eligibleForProgression":true,"enemyMissingPings":2,"enemyVisionPings":13,"firstBloodAssist":false,"firstBloodKill":false,"firstTowerAssist":false,"firstTowerKill":false,"gameEndedInEarlySurrender":false,"gameEndedInSurrender":false,"getBackPings":2,"goldEarned":18921,"goldSpent":17725,"holdPings":0,"individualPosition":"JUNGLE","inhibitorKills":0,"inhibitorTakedowns":0,"inhibitorsLost":4,"item0":3111,"item1":6699,"item2":3071,"item3":6333,"item4":3065,"item5":2501,"item6":3364,"itemsPurchased":29,"killingSprees":3,"kills":8,"lane":"JUNGLE","largestCriticalStrike":0,"largestKillingSpree":2,"largestMultiKill":2,"longestTimeSpentLiving":485,"magicDamageDealt":0,"magicDamageDealtToChampions":0,"magicDamageTaken":24096,"missions":{"playerScore0":0,"playerScore1":0,"playerScore2":0,"playerScore3":0,"playerScore4":0,"playerScore5":0,"playerScore6":0,"playerScore7":0,"playerScore8":0,"playerScore9":0,"playerScore10":0,"playerScore11":0},"needVisionPings":2,"neutralMinionsKilled":203,"nexusKills":0,"nexusLost":1,"nexusTakedowns":0,"objectivesStolen":0,"objectivesStolenAssists":0,"onMyWayPings":14,"participantId":7,"pentaKills":0,"perks":{"statPerks":{"defense":5001,"flex":5008,"offense":5008},"styles":[{"description":"primaryStyle","selections":[{"perk":8010,"var1":1330,"var2":0,"var3":0},{"perk":9111,"var1":2459,"var2":480,"var3":0},{"perk":9105,"var1":12,"var2":30,"var3":0},{"perk":8299,"var1":1633,"var2":0,"var3":0}],"style":8000},{"description":"subStyle","selections":[{"perk":8210,"var1":15,"var2":0,"var3":0},{"perk":8224,"var1":66,"var2":1922,"var3":0}],"style":8200}]},"physicalDamageDealt":347884,"physicalDamageDealtToChampions":56022,"physicalDamageTaken":46666,"placement":0,"playerAugment1":0,"playerAugment2":0,"playerAugment3":0,"playerAugment4":0,"playerAugment5":0,"playerAugment6":0,"playerSubteamId":0,"profileIcon":4976,"pushPings":1,"puuid":"LajF-rdN8yrvUzTWx5qA_Xv3iP1NGylRbt21qUwyVG5zzAQz8v9zJ1GefsASo3lex4xMPxRgMgSwKA","quadraKills":0,"retreatPings":1,"riotIdGameName":"Veylor","riotIdTagline":"4444","role":"NONE","sightWardsBoughtInGame":0,"spell1Casts":256,"spell2Casts":120,"spell3Casts":58,"spell4Casts":27,"subteamPlacement":0,"summoner1Casts":20,"summoner1Id":11,"summoner2Casts":5,"summoner2Id":4,"summonerId":"aCzxTDj7E6TqsCgsbN93OQMZgHrDhHdnDqCmJOTLK9ib9yg","summonerLevel":749,"summonerName":"","teamEarlySurrendered":false,"teamId":200,"teamPosition":"JUNGLE","timeCCingOthers":51,"timePlayed":2473,"totalAllyJungleMinionsKilled":139,"totalDamageDealt":421792,"totalDamageDealtToChampions":57030,"totalDamageShieldedOnTeammates":0,"totalDamageTaken":77687,"totalEnemyJungleMinionsKilled":12,"totalHeal":39690,"totalHealsOnTeammates":0,"totalMinionsKilled":89,"totalTimeCCDealt":639,"totalTimeSpentDead":311,"totalUnitsHealed":1,"tripleKills":0,"trueDamageDealt":73907,"trueDamageDealtToChampions":1007,"trueDamageTaken":6924,"turretKills":2,"turretTakedowns":2,"turretsLost":12,"unrealKills":0,"visionClearedPings":0,"visionScore":37,"visionWardsBoughtInGame":3,"wardsKilled":6,"wardsPlaced":4,"win":false},{"PlayerScore0":0,"PlayerScore1":0,"PlayerScore10":0,"PlayerScore11":0,"PlayerScore2":0,"PlayerScore3":0,"PlayerScore4":0,"PlayerScore5":0,"PlayerScore6":0,"PlayerScore7":0,"PlayerScore8":0,"PlayerScore9":0,"allInPings":0,"assistMePings":3,"assists":9,"baronKills":0,"basicPings":0,"challenges":{"12AssistStreakCount":0,"HealFromMapSources":1971.9018325805664,"InfernalScalePickup":0,"SWARM_DefeatAatrox":0,"SWARM_DefeatBriar":0,"SWARM_DefeatMiniBosses":0,"SWARM_EvolveWeapon":0,"SWARM_Have3Passives":0,"SWARM_KillEnemy":0,"SWARM_PickupGold":0,"SWARM_ReachLevel50":0,"SWARM_Survive15Min":0,"SWARM_WinWith5EvolvedWeapons":0,"abilityUses":404,"acesBefore15Minutes":0,"alliedJungleMonsterKills":0,"baronTakedowns":1,"blastConeOppositeOpponentCount":0,"bountyGold":1208.518295288086,"buffsStolen":0,"completeSupportQuestInTime":0,"controlWardsPlaced":0,"damagePerMinute":1152.3403689684606,"damageTakenOnTeamPercentage":0.23178253571093246,"dancedWithRiftHerald":0,"deathsByEnemyChamps":12,"dodgeSkillShotsSmallWindow":23,"doubleAces":0,"dragonTakedowns":1,"earliestBaron":2192.954524992,"earliestDragonTakedown":1997.9595202700002,"earlyLaningPhaseGoldExpAdvantage":0,"effectiveHealAndShielding":0,"elderDragonKillsWithOpposingSoul":0,"elderDragonMultikills":0,"enemyChampionImmobilizations":40,"enemyJungleMonsterKills":0,"epicMonsterKillsNearEnemyJungler":0,"epicMonsterKillsWithin30SecondsOfSpawn":0,"epicMonsterSteals":0,"epicMonsterStolenWithoutSmite":0,"firstTurretKilled":0,"fistBumpParticipation":0,"flawlessAces":1,"fullTeamTakedown":2,"gameLength":2473.2871889460002,"getTakedownsInAllLanesEarlyJungleAsLaner":0,"goldPerMinute":425.69526310192987,"hadOpenNexus":0,"immobilizeAndKillWithAlly":15,"initialBuffCount":0,"initialCrabCount":0,"jungleCsBefore10Minutes":0,"junglerTakedownsNearDamagedEpicMonster":0,"kTurretsDestroyedBeforePlatesFall":0,"kda":2.0833333333333335,"killAfterHiddenWithAlly":3,"killParticipation":0.5681818181818182,"killedChampTookFullTeamDamageSurvived":0,"killingSprees":3,"killsNearEnemyTurret":1,"killsOnOtherLanesEarlyJungleAsLaner":1,"killsOnRecentlyHealedByAramPack":0,"killsUnderOwnTurret":5,"killsWithHelpFromEpicMonster":0,"knockEnemyIntoTeamAndKill":0,"landSkillShotsEarlyGame":2,"laneMinionsFirst10Minutes":48,"laningPhaseGoldExpAdvantage":0,"legendaryCount":0,"legendaryItemUsed":[3152,4646,4629,3089,3157],"lostAnInhibitor":0,"maxCsAdvantageOnLaneOpponent":0,"maxKillDeficit":0,"maxLevelLeadLaneOpponent":1,"mejaisFullStackInTime":0,"moreEnemyJungleThanOpponent":0,"multiKillOneSpell":0,"multiTurretRiftHeraldCount":0,"multikills":1,"multikillsAfterAggressiveFlash":0,"outerTurretExecutesBefore10Minutes":0,"outnumberedKills":3,"outnumberedNexusKill":0,"perfectDragonSoulsTaken":0,"perfectGame":0,"pickKillWithAlly":18,"playedChampSelectPosition":1,"poroExplosions":0,"quickCleanse":0,"quickFirstTurret":0,"quickSoloKills":0,"riftHeraldTakedowns":1,"saveAllyFromDeath":0,"scuttleCrabKills":1,"skillshotsDodged":153,"skillshotsHit":14,"snowballsHit":0,"soloBaronKills":0,"soloKills":2,"stealthWardsPlaced":12,"survivedSingleDigitHpCount":0,"survivedThreeImmobilizesInFight":1,"takedownOnFirstTurret":0,"takedowns":25,"takedownsAfterGainingLevelAdvantage":0,"takedownsBeforeJungleMinionSpawn":0,"takedownsFirstXMinutes":7,"takedownsInAlcove":2,"takedownsInEnemyFountain":0,"teamBaronKills":1,"teamDamagePercentage":0.19496856303871193,"teamElderDragonKills":0,"teamRiftHeraldKills":1,"tookLargeDamageSurvived":0,"turretPlatesTaken":1,"turretTakedowns":0,"turretsTakenWithRiftHerald":5,"twentyMinionsIn3SecondsCount":0,"twoWardsOneSweeperCount":0,"unseenRecalls":0,"visionScoreAdvantageLaneOpponent":0.0021686553955078125,"visionScorePerMinute":0.5448280249616524,"voidMonsterKill":2,"wardTakedowns":1,"wardTakedownsBefore20M":0,"wardsGuarded":0},"champExperience":20848,"champLevel":18,"championId":517,"championName":"Sylas","championTransform":0,"commandPings":0,"consumablesPurchased":3,"damageDealtToBuildings":2331,"damageDealtToObjectives":13294,"damageDealtToTurrets":2331,"damageSelfMitigated":50505,"dangerPings":0,"deaths":12,"detectorWardsPlaced":0,"doubleKills":1,"dragonKills":0,"eligibleForProgression":true,"enemyMissingPings":8,"enemyVisionPings":0,"firstBloodAssist":false,"firstBloodKill":false,"firstTowerAssist":false,"firstTowerKill":false,"gameEndedInEarlySurrender":false,"gameEndedInSurrender":false,"getBackPings":3,"goldEarned":17547,"goldSpent":17450,"holdPings":0,"individualPosition":"MIDDLE","inhibitorKills":0,"inhibitorTakedowns":0,"inhibitorsLost":4,"item0":3111,"item1":3152,"item2":3157,"item3":4646,"item4":4629,"item5":3089,"item6":3364,"itemsPurchased":23,"killingSprees":4,"kills":16,"lane":"MIDDLE","largestCriticalStrike":0,"largestKillingSpree":4,"largestMultiKill":2,"longestTimeSpentLiving":464,"magicDamageDealt":173845,"magicDamageDealtToChampions":43440,"magicDamageTaken":24297,"missions":{"playerScore0":0,"playerScore1":0,"playerScore2":0,"playerScore3":0,"playerScore4":0,"playerScore5":0,"playerScore6":0,"playerScore7":0,"playerScore8":0,"playerScore9":0,"playerScore10":0,"playerScore11":0},"needVisionPings":0,"neutralMinionsKilled":4,"nexusKills":0,"nexusLost":1,"nexusTakedowns":0,"objectivesStolen":0,"objectivesStolenAssists":0,"onMyWayPings":5,"participantId":8,"pentaKills":0,"perks":{"statPerks":{"defense":5001,"flex":5008,"offense":5008},"styles":[{"description":"primaryStyle","selections":[{"perk":8112,"var1":3238,"var2":0,"var3":0},{"perk":8143,"var1":1774,"var2":0,"var3":0},{"perk":8140,"var1":18,"var2":0,"var3":0},{"perk":8105,"var1":40,"var2":5,"var3":0}],"style":8100},{"description":"subStyle","selections":[{"perk":9105,"var1":13,"var2":40,"var3":0},{"perk":8009,"var1":4474,"var2":0,"var3":0}],"style":8000}]},"physicalDamageDealt":9271,"physicalDamageDealtToChampions":477,"physicalDamageTaken":34812,"placement":0,"playerAugment1":0,"playerAugment2":0,"playerAugment3":0,"playerAugment4":0,"playerAugment5":0,"playerAugment6":0,"playerSubteamId":0,"profileIcon":1296,"pushPings":0,"puuid":"aOlhiK29CgG6yRLB8gQ-nPOB-zRy0GvQQcKQ_hjYzvt_QM1BbUUP2zW8dlhF0573c46EiPjk-tteJw","quadraKills":0,"retreatPings":4,"riotIdGameName":"Number76","riotIdTagline":"NA1","role":"SOLO","sightWardsBoughtInGame":0,"spell1Casts":117,"spell2Casts":75,"spell3Casts":173,"spell4Casts":39,"subteamPlacement":0,"summoner1Casts":10,"summoner1Id":14,"summoner2Casts":5,"summoner2Id":4,"summonerId":"yvz_SUx_17ddotzrhb-gNnLjxLecmA4ZZell-UNutsZfqfo","summonerLevel":530,"summonerName":"","teamEarlySurrendered":false,"teamId":200,"teamPosition":"MIDDLE","timeCCingOthers":42,"timePlayed":2473,"totalAllyJungleMinionsKilled":0,"totalDamageDealt":192432,"totalDamageDealtToChampions":47501,"totalDamageShieldedOnTeammates":0,"totalDamageTaken":60553,"totalEnemyJungleMinionsKilled":0,"totalHeal":10200,"totalHealsOnTeammates":0,"totalMinionsKilled":194,"totalTimeCCDealt":420,"totalTimeSpentDead":447,"totalUnitsHealed":1,"tripleKills":0,"trueDamageDealt":9314,"trueDamageDealtToChampions":3583,"trueDamageTaken":1443,"turretKills":0,"turretTakedowns":0,"turretsLost":12,"unrealKills":0,"visionClearedPings":0,"visionScore":22,"visionWardsBoughtInGame":0,"wardsKilled":1,"wardsPlaced":12,"win":false},{"PlayerScore0":0,"PlayerScore1":0,"PlayerScore10":0,"PlayerScore11":0,"PlayerScore2":0,"PlayerScore3":0,"PlayerScore4":0,"PlayerScore5":0,"PlayerScore6":0,"PlayerScore7":0,"PlayerScore8":0,"PlayerScore9":0,"allInPings":1,"assistMePings":16,"assists":15,"baronKills":0,"basicPings":0,"challenges":{"12AssistStreakCount":0,"HealFromMapSources":110,"InfernalScalePickup":0,"SWARM_DefeatAatrox":0,"SWARM_DefeatBriar":0,"SWARM_DefeatMiniBosses":0,"SWARM_EvolveWeapon":0,"SWARM_Have3Passives":0,"SWARM_KillEnemy":0,"SWARM_PickupGold":0,"SWARM_ReachLevel50":0,"SWARM_Survive15Min":0,"SWARM_WinWith5EvolvedWeapons":0,"abilityUses":281,"acesBefore15Minutes":0,"alliedJungleMonsterKills":1,"baronTakedowns":1,"blastConeOppositeOpponentCount":0,"bountyGold":0,"buffsStolen":0,"completeSupportQuestInTime":0,"controlWardsPlaced":0,"damagePerMinute":1177.9362074371738,"damageTakenOnTeamPercentage":0.11912438897245745,"dancedWithRiftHerald":0,"deathsByEnemyChamps":8,"dodgeSkillShotsSmallWindow":8,"doubleAces":0,"dragonTakedowns":1,"earliestBaron":2192.954524992,"earliestDragonTakedown":1997.9595202700002,"earlyLaningPhaseGoldExpAdvantage":0,"effectiveHealAndShielding":0,"elderDragonKillsWithOpposingSoul":0,"elderDragonMultikills":0,"enemyChampionImmobilizations":19,"enemyJungleMonsterKills":0,"epicMonsterKillsNearEnemyJungler":0,"epicMonsterKillsWithin30SecondsOfSpawn":0,"epicMonsterSteals":0,"epicMonsterStolenWithoutSmite":0,"firstTurretKilled":0,"fistBumpParticipation":0,"flawlessAces":1,"fullTeamTakedown":2,"gameLength":2473.2871889460002,"getTakedownsInAllLanesEarlyJungleAsLaner":0,"goldPerMinute":405.31439726463844,"hadOpenNexus":0,"immobilizeAndKillWithAlly":6,"initialBuffCount":0,"initialCrabCount":0,"jungleCsBefore10Minutes":0,"junglerTakedownsNearDamagedEpicMonster":0,"kTurretsDestroyedBeforePlatesFall":0,"kda":3,"killAfterHiddenWithAlly":2,"killParticipation":0.5454545454545454,"killedChampTookFullTeamDamageSurvived":0,"killingSprees":1,"killsNearEnemyTurret":2,"killsOnOtherLanesEarlyJungleAsLaner":0,"killsOnRecentlyHealedByAramPack":0,"killsUnderOwnTurret":1,"killsWithHelpFromEpicMonster":0,"knockEnemyIntoTeamAndKill":0,"landSkillShotsEarlyGame":0,"laneMinionsFirst10Minutes":50,"laningPhaseGoldExpAdvantage":0,"legendaryCount":0,"legendaryItemUsed":[3142,6676,3046,3046,3046,3033],"lostAnInhibitor":0,"maxCsAdvantageOnLaneOpponent":7,"maxKillDeficit":0,"maxLevelLeadLaneOpponent":1,"mejaisFullStackInTime":0,"moreEnemyJungleThanOpponent":0,"multiKillOneSpell":0,"multiTurretRiftHeraldCount":0,"multikills":0,"multikillsAfterAggressiveFlash":0,"outerTurretExecutesBefore10Minutes":0,"outnumberedKills":0,"outnumberedNexusKill":0,"perfectDragonSoulsTaken":0,"perfectGame":0,"pickKillWithAlly":20,"playedChampSelectPosition":1,"poroExplosions":0,"quickCleanse":0,"quickFirstTurret":0,"quickSoloKills":0,"riftHeraldTakedowns":0,"saveAllyFromDeath":0,"scuttleCrabKills":0,"shortestTimeToAceFromFirstTakedown":57.66259511199996,"skillshotsDodged":103,"skillshotsHit":26,"snowballsHit":0,"soloBaronKills":0,"soloKills":1,"stealthWardsPlaced":16,"survivedSingleDigitHpCount":0,"survivedThreeImmobilizesInFight":0,"takedownOnFirstTurret":0,"takedowns":24,"takedownsAfterGainingLevelAdvantage":0,"takedownsBeforeJungleMinionSpawn":0,"takedownsFirstXMinutes":3,"takedownsInAlcove":0,"takedownsInEnemyFountain":0,"teamBaronKills":1,"teamDamagePercentage":0.19929921393006556,"teamElderDragonKills":0,"teamRiftHeraldKills":1,"tookLargeDamageSurvived":0,"turretPlatesTaken":0,"turretTakedowns":3,"turretsTakenWithRiftHerald":5,"twentyMinionsIn3SecondsCount":0,"twoWardsOneSweeperCount":0,"unseenRecalls":0,"visionScoreAdvantageLaneOpponent":-0.41135740280151367,"visionScorePerMinute":0.5805980186601146,"voidMonsterKill":1,"wardTakedowns":1,"wardTakedownsBefore20M":0,"wardsGuarded":0},"champExperience":21851,"champLevel":18,"championId":202,"championName":"Jhin","championTransform":0,"commandPings":15,"consumablesPurchased":6,"damageDealtToBuildings":3496,"damageDealtToObjectives":17299,"damageDealtToTurrets":3496,"damageSelfMitigated":20546,"dangerPings":0,"deaths":8,"detectorWardsPlaced":0,"doubleKills":0,"dragonKills":0,"eligibleForProgression":true,"enemyMissingPings":9,"enemyVisionPings":3,"firstBloodAssist":false,"firstBloodKill":false,"firstTowerAssist":false,"firstTowerKill":false,"gameEndedInEarlySurrender":false,"gameEndedInSurrender":false,"getBackPings":5,"goldEarned":16707,"goldSpent":16600,"holdPings":0,"individualPosition":"BOTTOM","inhibitorKills":0,"inhibitorTakedowns":0,"inhibitorsLost":4,"item0":6676,"item1":3009,"item2":3142,"item3":3046,"item4":1053,"item5":3033,"item6":3340,"itemsPurchased":35,"killingSprees":2,"kills":9,"lane":"BOTTOM","largestCriticalStrike":1804,"largestKillingSpree":4,"largestMultiKill":1,"longestTimeSpentLiving":546,"magicDamageDealt":27319,"magicDamageDealtToChampions":2141,"magicDamageTaken":13245,"missions":{"playerScore0":0,"playerScore1":0,"playerScore2":0,"playerScore3":0,"playerScore4":0,"playerScore5":0,"playerScore6":0,"playerScore7":0,"playerScore8":0,"playerScore9":0,"playerScore10":0,"playerScore11":0},"needVisionPings":0,"neutralMinionsKilled":4,"nexusKills":0,"nexusLost":1,"nexusTakedowns":0,"objectivesStolen":0,"objectivesStolenAssists":0,"onMyWayPings":20,"participantId":9,"pentaKills":0,"perks":{"statPerks":{"defense":5001,"flex":5008,"offense":5008},"styles":[{"description":"primaryStyle","selections":[{"perk":8021,"var1":2315,"var2":0,"var3":0},{"perk":8009,"var1":2684,"var2":0,"var3":0},{"perk":9103,"var1":25,"var2":20,"var3":0},{"perk":8014,"var1":1130,"var2":0,"var3":0}],"style":8000},{"description":"subStyle","selections":[{"perk":8234,"var1":19203,"var2":0,"var3":0},{"perk":8236,"var1":48,"var2":0,"var3":0}],"style":8200}]},"physicalDamageDealt":227314,"physicalDamageDealtToChampions":45081,"physicalDamageTaken":16603,"placement":0,"playerAugment1":0,"playerAugment2":0,"playerAugment3":0,"playerAugment4":0,"playerAugment5":0,"playerAugment6":0,"playerSubteamId":0,"profileIcon":6017,"pushPings":0,"puuid":"OkHv4J5JcbqQSx9I5Fda7L9rpz4wQcaDVpgDyjtlhEcpdZIM9ExEyrfTpjS6EdsYcZjKX9i5ctKC9A","quadraKills":0,"retreatPings":0,"riotIdGameName":"S1NE","riotIdTagline":"NA1","role":"CARRY","sightWardsBoughtInGame":0,"spell1Casts":113,"spell2Casts":53,"spell3Casts":76,"spell4Casts":39,"subteamPlacement":0,"summoner1Casts":7,"summoner1Id":21,"summoner2Casts":6,"summoner2Id":4,"summonerId":"SMdSDPG7aDUYglyHAuXJ4mif9ge7hyjnW2gfSXPnLexSrh0","summonerLevel":556,"summonerName":"","teamEarlySurrendered":false,"teamId":200,"teamPosition":"BOTTOM","timeCCingOthers":48,"timePlayed":2473,"totalAllyJungleMinionsKilled":4,"totalDamageDealt":257421,"totalDamageDealtToChampions":48556,"totalDamageShieldedOnTeammates":0,"totalDamageTaken":31121,"totalEnemyJungleMinionsKilled":0,"totalHeal":8550,"totalHealsOnTeammates":0,"totalMinionsKilled":217,"totalTimeCCDealt":298,"totalTimeSpentDead":250,"totalUnitsHealed":1,"tripleKills":0,"trueDamageDealt":2787,"trueDamageDealtToChampions":1333,"trueDamageTaken":1272,"turretKills":1,"turretTakedowns":3,"turretsLost":12,"unrealKills":0,"visionClearedPings":0,"visionScore":23,"visionWardsBoughtInGame":0,"wardsKilled":1,"wardsPlaced":16,"win":false},{"PlayerScore0":0,"PlayerScore1":0,"PlayerScore10":0,"PlayerScore11":0,"PlayerScore2":0,"PlayerScore3":0,"PlayerScore4":0,"PlayerScore5":0,"PlayerScore6":0,"PlayerScore7":0,"PlayerScore8":0,"PlayerScore9":0,"allInPings":0,"assistMePings":0,"assists":21,"baronKills":0,"basicPings":0,"challenges":{"12AssistStreakCount":1,"HealFromMapSources":68,"InfernalScalePickup":0,"SWARM_DefeatAatrox":0,"SWARM_DefeatBriar":0,"SWARM_DefeatMiniBosses":0,"SWARM_EvolveWeapon":0,"SWARM_Have3Passives":0,"SWARM_KillEnemy":0,"SWARM_PickupGold":0,"SWARM_ReachLevel50":0,"SWARM_Survive15Min":0,"SWARM_WinWith5EvolvedWeapons":0,"abilityUses":214,"acesBefore15Minutes":0,"alliedJungleMonsterKills":1,"baronTakedowns":1,"blastConeOppositeOpponentCount":0,"bountyGold":361.2416687011719,"buffsStolen":0,"completeSupportQuestInTime":0,"controlWardTimeCoverageInRiverOrEnemyHalf":0.4717664322396146,"controlWardsPlaced":2,"damagePerMinute":744.3942261754048,"damageTakenOnTeamPercentage":0.13692211262546924,"dancedWithRiftHerald":0,"deathsByEnemyChamps":9,"dodgeSkillShotsSmallWindow":1,"doubleAces":0,"dragonTakedowns":1,"earliestBaron":2192.954524992,"earliestDragonTakedown":596.9472779040001,"earlyLaningPhaseGoldExpAdvantage":0,"effectiveHealAndShielding":11751.4111328125,"elderDragonKillsWithOpposingSoul":0,"elderDragonMultikills":0,"enemyChampionImmobilizations":42,"enemyJungleMonsterKills":1,"epicMonsterKillsNearEnemyJungler":0,"epicMonsterKillsWithin30SecondsOfSpawn":0,"epicMonsterSteals":0,"epicMonsterStolenWithoutSmite":0,"firstTurretKilled":0,"fistBumpParticipation":0,"flawlessAces":1,"fullTeamTakedown":2,"gameLength":2473.2871889460002,"getTakedownsInAllLanesEarlyJungleAsLaner":0,"goldPerMinute":315.72320579925145,"hadOpenNexus":0,"highestWardKills":1,"immobilizeAndKillWithAlly":7,"initialBuffCount":0,"initialCrabCount":0,"jungleCsBefore10Minutes":0,"junglerTakedownsNearDamagedEpicMonster":0,"kTurretsDestroyedBeforePlatesFall":0,"kda":2.6666666666666665,"killAfterHiddenWithAlly":2,"killParticipation":0.5454545454545454,"killedChampTookFullTeamDamageSurvived":0,"killingSprees":0,"killsNearEnemyTurret":0,"killsOnOtherLanesEarlyJungleAsLaner":0,"killsOnRecentlyHealedByAramPack":0,"killsUnderOwnTurret":0,"killsWithHelpFromEpicMonster":0,"knockEnemyIntoTeamAndKill":0,"landSkillShotsEarlyGame":5,"laneMinionsFirst10Minutes":8,"laningPhaseGoldExpAdvantage":0,"legendaryCount":0,"legendaryItemUsed":[3877,3071,3094,3031],"lostAnInhibitor":0,"maxCsAdvantageOnLaneOpponent":17.400000005960464,"maxKillDeficit":0,"maxLevelLeadLaneOpponent":2,"mejaisFullStackInTime":0,"moreEnemyJungleThanOpponent":0,"multiKillOneSpell":0,"multiTurretRiftHeraldCount":0,"multikills":1,"multikillsAfterAggressiveFlash":0,"outerTurretExecutesBefore10Minutes":0,"outnumberedKills":0,"outnumberedNexusKill":0,"perfectDragonSoulsTaken":0,"perfectGame":0,"pickKillWithAlly":19,"playedChampSelectPosition":1,"poroExplosions":0,"quickCleanse":0,"quickFirstTurret":0,"quickSoloKills":0,"riftHeraldTakedowns":0,"saveAllyFromDeath":2,"scuttleCrabKills":0,"skillshotsDodged":68,"skillshotsHit":60,"snowballsHit":0,"soloBaronKills":0,"soloKills":0,"stealthWardsPlaced":28,"survivedSingleDigitHpCount":0,"survivedThreeImmobilizesInFight":0,"takedownOnFirstTurret":0,"takedowns":24,"takedownsAfterGainingLevelAdvantage":0,"takedownsBeforeJungleMinionSpawn":0,"takedownsFirstXMinutes":3,"takedownsInAlcove":0,"takedownsInEnemyFountain":0,"teamBaronKills":1,"teamDamagePercentage":0.1259467050882298,"teamElderDragonKills":0,"teamRiftHeraldKills":1,"tookLargeDamageSurvived":0,"turretPlatesTaken":0,"turretTakedowns":1,"turretsTakenWithRiftHerald":5,"twentyMinionsIn3SecondsCount":0,"twoWardsOneSweeperCount":0,"unseenRecalls":0,"visionScoreAdvantageLaneOpponent":-0.1892307996749878,"visionScorePerMinute":1.7967269990955779,"voidMonsterKill":1,"wardTakedowns":11,"wardTakedownsBefore20M":5,"wardsGuarded":1},"champExperience":16997,"champLevel":17,"championId":235,"championName":"Senna","championTransform":0,"commandPings":3,"consumablesPurchased":5,"damageDealtToBuildings":1850,"damageDealtToObjectives":8949,"damageDealtToTurrets":1850,"damageSelfMitigated":19057,"dangerPings":0,"deaths":9,"detectorWardsPlaced":2,"doubleKills":1,"dragonKills":0,"eligibleForProgression":true,"enemyMissingPings":0,"enemyVisionPings":23,"firstBloodAssist":false,"firstBloodKill":false,"firstTowerAssist":false,"firstTowerKill":false,"gameEndedInEarlySurrender":false,"gameEndedInSurrender":false,"getBackPings":0,"goldEarned":13014,"goldSpent":12000,"holdPings":0,"individualPosition":"UTILITY","inhibitorKills":0,"inhibitorTakedowns":0,"inhibitorsLost":4,"item0":3877,"item1":3009,"item2":3071,"item3":3094,"item4":3031,"item5":3051,"item6":3364,"itemsPurchased":26,"killingSprees":1,"kills":3,"lane":"BOTTOM","largestCriticalStrike":748,"largestKillingSpree":2,"largestMultiKill":2,"longestTimeSpentLiving":499,"magicDamageDealt":863,"magicDamageDealtToChampions":368,"magicDamageTaken":20525,"missions":{"playerScore0":0,"playerScore1":0,"playerScore2":0,"playerScore3":0,"playerScore4":0,"playerScore5":0,"playerScore6":0,"playerScore7":0,"playerScore8":0,"playerScore9":0,"playerScore10":0,"playerScore11":0},"needVisionPings":0,"neutralMinionsKilled":4,"nexusKills":0,"nexusLost":1,"nexusTakedowns":0,"objectivesStolen":0,"objectivesStolenAssists":0,"onMyWayPings":0,"participantId":10,"pentaKills":0,"perks":{"statPerks":{"defense":5001,"flex":5008,"offense":5005},"styles":[{"description":"primaryStyle","selections":[{"perk":8021,"var1":2254,"var2":0,"var3":0},{"perk":8009,"var1":3359,"var2":0,"var3":0},{"perk":9104,"var1":21,"var2":50,"var3":0},{"perk":8017,"var1":1491,"var2":0,"var3":0}],"style":8000},{"description":"subStyle","selections":[{"perk":8473,"var1":601,"var2":0,"var3":0},{"perk":8453,"var1":1850,"var2":675,"var3":0}],"style":8400}]},"physicalDamageDealt":68399,"physicalDamageDealtToChampions":29408,"physicalDamageTaken":14279,"placement":0,"playerAugment1":0,"playerAugment2":0,"playerAugment3":0,"playerAugment4":0,"playerAugment5":0,"playerAugment6":0,"playerSubteamId":0,"profileIcon":6876,"pushPings":0,"puuid":"VJweImMEIgwDU5oaaiRb0cA9aV_VZ4N4XQMyqKodETtZGeRLDdKpYDwFqjICkZTgYwM2PDYpISsMlQ","quadraKills":0,"retreatPings":0,"riotIdGameName":"MlDEN","riotIdTagline":"NA1","role":"SUPPORT","sightWardsBoughtInGame":0,"spell1Casts":93,"spell2Casts":57,"spell3Casts":52,"spell4Casts":12,"subteamPlacement":0,"summoner1Casts":8,"summoner1Id":7,"summoner2Casts":6,"summoner2Id":4,"summonerId":"jj6XqnG0bvC8426SMli9wjZu4HycG8_ysSNfaPxPoYd3cCk","summonerLevel":498,"summonerName":"","teamEarlySurrendered":false,"teamId":200,"teamPosition":"UTILITY","timeCCingOthers":83,"timePlayed":2473,"totalAllyJungleMinionsKilled":0,"totalDamageDealt":71569,"totalDamageDealtToChampions":30685,"totalDamageShieldedOnTeammates":4451,"totalDamageTaken":35771,"totalEnemyJungleMinionsKilled":4,"totalHeal":18954,"totalHealsOnTeammates":7300,"totalMinionsKilled":48,"totalTimeCCDealt":283,"totalTimeSpentDead":270,"totalUnitsHealed":5,"tripleKills":0,"trueDamageDealt":2306,"trueDamageDealtToChampions":908,"trueDamageTaken":966,"turretKills":1,"turretTakedowns":1,"turretsLost":12,"unrealKills":0,"visionClearedPings":0,"visionScore":74,"visionWardsBoughtInGame":2,"wardsKilled":11,"wardsPlaced":30,"win":false}],"platformId":"NA1","queueId":420,"teams":[{"bans":[{"championId":17,"pickTurn":1},{"championId":56,"pickTurn":2},{"championId":238,"pickTurn":3},{"championId":234,"pickTurn":4},{"championId":122,"pickTurn":5}],"feats":{"EPIC_MONSTER_KILL":{"featState":1},"FIRST_BLOOD":{"featState":3},"FIRST_TURRET":{"featState":1}},"objectives":{"atakhan":{"first":false,"kills":0},"baron":{"first":true,"kills":1},"champion":{"first":true,"kills":48},"dragon":{"first":false,"kills":4},"horde":{"first":true,"kills":3},"inhibitor":{"first":true,"kills":4},"riftHerald":{"first":false,"kills":0},"tower":{"first":true,"kills":12}},"teamId":100,"win":true},{"bans":[{"championId":83,"pickTurn":6},{"championId":-1,"pickTurn":7},{"championId":910,"pickTurn":8},{"championId":82,"pickTurn":9},{"championId":222,"pickTurn":10}],"feats":{"EPIC_MONSTER_KILL":{"featState":1},"FIRST_BLOOD":{"featState":1001},"FIRST_TURRET":{"featState":1001}},"objectives":{"atakhan":{"first":true,"kills":1},"baron":{"first":false,"kills":1},"champion":{"first":false,"kills":44},"dragon":{"first":true,"kills":2},"horde":{"first":false,"kills":0},"inhibitor":{"first":false,"kills":0},"riftHerald":{"first":true,"kills":1},"tower":{"first":false,"kills":5}},"teamId":200,"win":false}],"tournamentCode":""}}}